ECOv003_L3T_L4T_JET/ECOv002-cal-val-JET-inputs.csv
ECOv003_L3T_L4T_JET/ECOv002-cal-val-JET-outputs.csv
ECOv003_L3T_L4T_JET/ECOv002_calval_JET_inputs.py
ECOv003_L3T_L4T_JET/ECOv003_L3T_L4T_JET.py
ECOv003_L3T_L4T_JET/JET.py
ECOv003_L3T_L4T_JET/L3TL4TJETConfig.py
ECOv003_L3T_L4T_JET/L3T_L4T_JET.xml
ECOv003_L3T_L4T_JET/__init__.py
ECOv003_L3T_L4T_JET/constants.py
ECOv003_L3T_L4T_JET/exceptions.py
ECOv003_L3T_L4T_JET/generate_L3T_L4T_JET_runconfig.py
ECOv003_L3T_L4T_JET/process_JET_table.py
ECOv003_L3T_L4T_JET/read_ECOv003_configuration.py
ECOv003_L3T_L4T_JET/read_ECOv003_inputs.py
ECOv003_L3T_L4T_JET/runconfig.py
ECOv003_L3T_L4T_JET/sharpen_meteorology_data.py
ECOv003_L3T_L4T_JET/sharpen_soil_moisture_data.py
ECOv003_L3T_L4T_JET/verify.py
ECOv003_L3T_L4T_JET/version.py
ECOv003_L3T_L4T_JET/write_ECOv003_products.py
documentation/ECOv003_L3_L4_JET_ATBD.md
documentation/ECOv003_L3_L4_JET_ATBD.pdf
documentation/ECOv003_L3_L4_JET_ATBD.sh
documentation/ECOv003_L3_L4_JET_User_Guide.md
documentation/ECOv003_L3_L4_JET_User_Guide.pdf
documentation/ECOv003_L3_L4_JET_User_Guide.sh
ecov003_l3t_l4t_jet-1.16.0.dist-info/licenses/LICENSE
tests/conftest.py
tests/test_import_ECOv003_L3T_L4T_JET.py
tests/test_import_dependencies.py
tests/test_verify.py
ecov003_l3t_l4t_jet-1.16.0.dist-info/METADATA
ecov003_l3t_l4t_jet-1.16.0.dist-info/WHEEL
ecov003_l3t_l4t_jet-1.16.0.dist-info/entry_points.txt
ecov003_l3t_l4t_jet-1.16.0.dist-info/top_level.txt
ecov003_l3t_l4t_jet-1.16.0.dist-info/RECORD
