Metadata-Version: 2.4
Name: ECOv003-L3T-L4T-JET
Version: 1.16.0
Summary: ECOSTRESS Collection 3 JPL Evapotranspiration (JET) Product Generating Executable (PGE)
Author-email: "Gregory H. Halverson" <gregory.h.halverson@jpl.nasa.gov>
Project-URL: Homepage, https://github.com/ECOSTRESS-Collection-2/ECOv003-L3T-L4T-JET
Classifier: Programming Language :: Python :: 3
Classifier: Operating System :: OS Independent
Requires-Python: >=3.10
License-File: LICENSE
Requires-Dist: AquaSEBS~=1.3.0
Requires-Dist: BESS-JPL~=1.28.0
Requires-Dist: check-distribution~=1.2.0
Requires-Dist: colored-logging~=1.1.0
Requires-Dist: ECOv002-calval-tables~=1.11.0
Requires-Dist: ECOv002-granules~=1.2.1
Requires-Dist: ECOv003-exit-codes~=1.1.0
Requires-Dist: ECOv003-granules~=1.13.1
Requires-Dist: FLiESANN~=2.13.0
Requires-Dist: GEOS5FP~=2.19.0
Requires-Dist: koppengeiger~=1.1.0
Requires-Dist: monte-carlo-sensitivity~=1.9.1
Requires-Dist: numpy~=2.2.0
Requires-Dist: pandas~=2.2.0
Requires-Dist: PM-JPL~=1.11.0
Requires-Dist: PTJPLSM~=1.10.0
Requires-Dist: python-dateutil~=2.9.0
Requires-Dist: pytictoc~=1.5.3
Requires-Dist: rasters~=1.17.1
Requires-Dist: rasterio~=1.4.0
Requires-Dist: scikit-learn~=1.7.0
Requires-Dist: solar-apparent-time~=1.5.4
Requires-Dist: STIC-JPL~=1.6.0
Requires-Dist: sun-angles~=1.7.0
Requires-Dist: untangle~=1.2.1
Requires-Dist: verma-net-radiation~=1.11.0
Provides-Extra: dev
Requires-Dist: build; extra == "dev"
Requires-Dist: pytest>=6.0; extra == "dev"
Requires-Dist: pytest-cov; extra == "dev"
Requires-Dist: jupyter; extra == "dev"
Requires-Dist: pytest; extra == "dev"
Requires-Dist: twine; extra == "dev"
Dynamic: license-file
